toolong/__init__.py
toolong/__main__.py
toolong/cli.py
toolong/find_dialog.py
toolong/format_parser.py
toolong/goto_screen.py
toolong/help.py
toolong/highlighter.py
toolong/line_panel.py
toolong/log_file.py
toolong/log_lines.py
toolong/log_view.py
toolong/messages.py
toolong/poll_watcher.py
toolong/scan_progress_bar.py
toolong/selector_watcher.py
toolong/timestamps.py
toolong/ui.py
toolong/watcher.py
toolong-1.5.0.dist-info/LICENSE
toolong-1.5.0.dist-info/METADATA
toolong-1.5.0.dist-info/WHEEL
toolong-1.5.0.dist-info/entry_points.txt
toolong-1.5.0.dist-info/RECORD
