Metadata-Version: 2.1
Name: toolong
Version: 1.5.0
Summary: A terminal log file viewer / tailer / analyzer
Home-page: https://github.com/textualize/toolong
License: MIT
Author: Will McGugan
Author-email: will@textualize.io
Requires-Python: >=3.8,<4.0
Classifier: License :: OSI Approved :: MIT License
Classifier: Programming Language :: Python :: 3
Classifier: Programming Language :: Python :: 3.8
Classifier: Programming Language :: Python :: 3.9
Classifier: Programming Language :: Python :: 3.10
Classifier: Programming Language :: Python :: 3.11
Classifier: Programming Language :: Python :: 3.12
Requires-Dist: click (>=8.1.7,<9.0.0)
Requires-Dist: textual (>=0.58.0,<0.59.0)
Requires-Dist: typing-extensions (>=4.9.0,<5.0.0)
Project-URL: Documentation, https://github.com/textualize/toolong
Project-URL: Repository, https://github.com/textualize/toolong
